<events>
  <event>
    <cause-var>50</cause-var>
    <created-at>2014-04-05T06:11:59Z</created-at>
    <data-var1>2399</data-var1>
    <data-var10>0 °C/0 °C</data-var10>
    <data-var11>0 °C/0 °C</data-var11>
    <data-var12>0 °C/0 °C</data-var12>
    <data-var2>175</data-var2>
    <data-var3>0</data-var3>
    <data-var4>0</data-var4>
    <data-var5>0</data-var5>
    <data-var6>0</data-var6>
    <data-var7>13</data-var7>
    <data-var8>25 °C/30 °C</data-var8>
    <data-var9>30 °C/31 °C</data-var9>
    <error-level>1</error-level>
    <error-nr>25</error-nr>
    <event>4A38C60B880019000000010000000000320000005F09AF0000000000000000000D001E191F1E000000000000</event>
    <info-flags>0</info-flags>
    <issue nil="true"/>
    <module-id>136</module-id>
    <module-state>0</module-state>
    <prev-module-state>0</prev-module-state>
    <time-send>2014-04-05T08:11:55Z</time-send>
    <time-stamp>2014-04-05T08:11:54Z</time-stamp>
  </event>
  <event>
    <cause-var>0</cause-var>
    <created-at>2014-04-05T08:42:54Z</created-at>
    <data-var1>0</data-var1>
    <data-var10>0</data-var10>
    <data-var11>200</data-var11>
    <data-var12>0</data-var12>
    <data-var2>1</data-var2>
    <data-var3>0</data-var3>
    <data-var4>80</data-var4>
    <data-var5>-28646</data-var5>
    <data-var6>118</data-var6>
    <data-var7>0</data-var7>
    <data-var8>400</data-var8>
    <data-var9>-11335</data-var9>
    <error-level>2</error-level>
    <error-nr>16</error-nr>
    <event>A85BC60B0C00100001000200000000000000000000000100000050001A90760000009001B9D30000C8000000</event>
    <info-flags>0</info-flags>
    <issue nil="true"/>
    <module-id>12</module-id>
    <module-state>1</module-state>
    <prev-module-state>0</prev-module-state>
    <time-send>2014-04-05T10:42:49Z</time-send>
    <time-stamp>2014-04-05T10:42:48Z</time-stamp>
  </event>
  <event>
    <cause-var>0</cause-var>
    <created-at>2014-04-05T08:42:57Z</created-at>
    <data-var1>0</data-var1>
    <data-var10>0</data-var10>
    <data-var11>200</data-var11>
    <data-var12>0</data-var12>
    <data-var2>1</data-var2>
    <data-var3>0</data-var3>
    <data-var4>80</data-var4>
    <data-var5>-23209</data-var5>
    <data-var6>0</data-var6>
    <data-var7>0</data-var7>
    <data-var8>390</data-var8>
    <data-var9>-23241</data-var9>
    <error-level>130</error-level>
    <error-nr>16</error-nr>
    <event>AD5BC60B0C001000030082000000000000000000000001000000500057A500000000860137A50000C8000000</event>
    <info-flags>0</info-flags>
    <issue nil="true"/>
    <module-id>12</module-id>
    <module-state>3</module-state>
    <prev-module-state>0</prev-module-state>
    <time-send>2014-04-05T10:42:53Z</time-send>
    <time-stamp>2014-04-05T10:42:53Z</time-stamp>
  </event>
  <event>
    <cause-var>0</cause-var>
    <created-at>2014-04-05T08:46:59Z</created-at>
    <data-var1>278</data-var1>
    <data-var10>2328</data-var10>
    <data-var11>0</data-var11>
    <data-var12>5002</data-var12>
    <data-var2>17</data-var2>
    <data-var3>3840</data-var3>
    <data-var4>0</data-var4>
    <data-var5>0</data-var5>
    <data-var6>18</data-var6>
    <data-var7>0</data-var7>
    <data-var8>12</data-var8>
    <data-var9>1</data-var9>
    <error-level>0</error-level>
    <error-nr>5</error-nr>
    <event>9E5CC60B1000050002020000000000000000000016011100000F00000000120000000C000100180900008A13</event>
    <info-flags>0</info-flags>
    <issue nil="true"/>
    <module-id>16</module-id>
    <module-state>2</module-state>
    <prev-module-state>2</prev-module-state>
    <time-send>2014-04-05T10:46:55Z</time-send>
    <time-stamp>2014-04-05T10:46:54Z</time-stamp>
  </event>
  <event>
    <cause-var>-570</cause-var>
    <created-at>2014-04-05T10:31:12Z</created-at>
    <data-var1>278</data-var1>
    <data-var10>2358</data-var10>
    <data-var11>0</data-var11>
    <data-var12>5001</data-var12>
    <data-var2>17</data-var2>
    <data-var3>3328</data-var3>
    <data-var4>0</data-var4>
    <data-var5>0</data-var5>
    <data-var6>18</data-var6>
    <data-var7>0</data-var7>
    <data-var8>12</data-var8>
    <data-var9>1</data-var9>
    <error-level>1</error-level>
    <error-nr>110</error-nr>
    <event>0A75C60B10006E000202010000000000C6FDFFFF16011100000D00000000120000000C000100360900008913</event>
    <info-flags>0</info-flags>
    <issue nil="true"/>
    <module-id>16</module-id>
    <module-state>2</module-state>
    <prev-module-state>2</prev-module-state>
    <time-send>2014-04-05T12:31:07Z</time-send>
    <time-stamp>2014-04-05T12:31:06Z</time-stamp>
  </event>
  <event>
    <cause-var>-26</cause-var>
    <created-at>2014-04-05T11:23:14Z</created-at>
    <data-var1>278</data-var1>
    <data-var10>2362</data-var10>
    <data-var11>0</data-var11>
    <data-var12>5000</data-var12>
    <data-var2>17</data-var2>
    <data-var3>3328</data-var3>
    <data-var4>0</data-var4>
    <data-var5>0</data-var5>
    <data-var6>18</data-var6>
    <data-var7>0</data-var7>
    <data-var8>12</data-var8>
    <data-var9>1</data-var9>
    <error-level>1</error-level>
    <error-nr>109</error-nr>
    <event>3C81C60B10006D000202010000000000E6FFFFFF16011100000D00000000120000000C0001003A0900008813</event>
    <info-flags>0</info-flags>
    <issue nil="true"/>
    <module-id>16</module-id>
    <module-state>2</module-state>
    <prev-module-state>2</prev-module-state>
    <time-send>2014-04-05T13:23:09Z</time-send>
    <time-stamp>2014-04-05T13:23:08Z</time-stamp>
  </event>
</events>
